classification_reportzr/VERSION
classification_reportzr/reporterzr.py
tests/__init__.py
tests/test_reporterzr.py
classification_reportzr-0.0.1b9.dist-info/METADATA
classification_reportzr-0.0.1b9.dist-info/WHEEL
classification_reportzr-0.0.1b9.dist-info/top_level.txt
classification_reportzr-0.0.1b9.dist-info/RECORD
